.gitignore
HISTORY.txt
LICENSE
MANIFEST.in
README.rst
setup.cfg
setup.py
cabot_alert_telegram/__init__.py
cabot_alert_telegram/models.py
cabot_alert_telegram.egg-info/PKG-INFO
cabot_alert_telegram.egg-info/SOURCES.txt
cabot_alert_telegram.egg-info/dependency_links.txt
cabot_alert_telegram.egg-info/not-zip-safe
cabot_alert_telegram.egg-info/requires.txt
cabot_alert_telegram.egg-info/top_level.txt
cabot_alert_telegram/migrations/0001_initial.py
cabot_alert_telegram/migrations/__init__.py
cabot_alert_telegram/tests/__init__.py