Metadata-Version: 1.0
Name: cabot-alert-telegram
Version: 0.6
Summary: A Telegram alert plugin for Cabot by Arachnys
Home-page: https://github.com/codesyntax/cabot_alert_telegram
Author: Mikel Larreategi
Author-email: mlarreategi@codesyntax.com
License: GPL
Platform: UNKNOWN
